{
  "pageno": 0,
  "pagesize": 0,
  "totalcount": 100,
  "contacts": [
    {
      "no": 1587142805767,
      "name": "Keandra Edwards",
      "tel": "010-3456-8299",
      "address": "서울시",
      "photo": "http://sample.bmaster.kro.kr/photos/100.jpg"
    },
    {
      "no": 1587142805766,
      "name": "Katherine Johnson",
      "tel": "010-3456-8298",
      "address": "서울시",
      "photo": "http://sample.bmaster.kro.kr/photos/99.jpg"
    },
    {
      "no": 1587142805765,
      "name": "Katchi Lee",
      "tel": "010-3456-8297",
      "address": "서울시",
      "photo": "http://sample.bmaster.kro.kr/photos/98.jpg"
    },
    {
      "no": 1587142805764,
      "name": "Kalisa Reyes",
      "tel": "010-3456-8296",
      "address": "서울시",
      "photo": "http://sample.bmaster.kro.kr/photos/97.jpg"
    },
    {
      "no": 1587142805763,
      "name": "Jesse Cox",
      "tel": "010-3456-8295",
      "address": "서울시",
      "photo": "http://sample.bmaster.kro.kr/photos/96.jpg"
    },
    {
      "no": 1587142805762,
      "name": "Jennifer Sanders",
      "tel": "010-3456-8294",
      "address": "서울시",
      "photo": "http://sample.bmaster.kro.kr/photos/95.jpg"
    },
    {
      "no": 1587142805761,
      "name": "Ambrosia Sullivan",
      "tel": "010-3456-8293",
      "address": "서울시",
      "photo": "http://sample.bmaster.kro.kr/photos/94.jpg"
    },
    {
      "no": 1587142805760,
      "name": "Isabelle Adams",
      "tel": "010-3456-8292",
      "address": "서울시",
      "photo": "http://sample.bmaster.kro.kr/photos/93.jpg"
    },
    {
      "no": 1587142805759,
      "name": "Victoria Robinson",
      "tel": "010-3456-8291",
      "address": "서울시",
      "photo": "http://sample.bmaster.kro.kr/photos/92.jpg"
    },
    {
      "no": 1587142805758,
      "name": "Isabella Johnson",
      "tel": "010-3456-8290",
      "address": "서울시",
      "photo": "http://sample.bmaster.kro.kr/photos/91.jpg"
    },
    {
      "no": 1587142805757,
      "name": "Francess Young",
      "tel": "010-3456-8289",
      "address": "서울시",
      "photo": "http://sample.bmaster.kro.kr/photos/90.jpg"
    },
    {
      "no": 1587142805756,
      "name": "Lin Nguyen",
      "tel": "010-3456-8288",
      "address": "서울시",
      "photo": "http://sample.bmaster.kro.kr/photos/89.jpg"
    },
    {
      "no": 1587142805755,
      "name": "Catera Morgan",
      "tel": "010-3456-8287",
      "address": "서울시",
      "photo": "http://sample.bmaster.kro.kr/photos/88.jpg"
    },
    {
      "no": 1587142805754,
      "name": "Emani Baker",
      "tel": "010-3456-8286",
      "address": "서울시",
      "photo": "http://sample.bmaster.kro.kr/photos/87.jpg"
    },
    {
      "no": 1587142805753,
      "name": "Caroline Rivera",
      "tel": "010-3456-8285",
      "address": "서울시",
      "photo": "http://sample.bmaster.kro.kr/photos/86.jpg"
    },
    {
      "no": 1587142805752,
      "name": "Annabelle Lewis",
      "tel": "010-3456-8284",
      "address": "서울시",
      "photo": "http://sample.bmaster.kro.kr/photos/85.jpg"
    },
    {
      "no": 1587142805751,
      "name": "Aveen Bell",
      "tel": "010-3456-8283",
      "address": "서울시",
      "photo": "http://sample.bmaster.kro.kr/photos/84.jpg"
    },
    {
      "no": 1587142805750,
      "name": "Alania Wilson",
      "tel": "010-3456-8282",
      "address": "서울시",
      "photo": "http://sample.bmaster.kro.kr/photos/83.jpg"
    },
    {
      "no": 1587142805749,
      "name": "Zenon Miller",
      "tel": "010-3456-8281",
      "address": "서울시",
      "photo": "http://sample.bmaster.kro.kr/photos/82.jpg"
    },
    {
      "no": 1587142805748,
      "name": "Kylie Cook",
      "tel": "010-3456-8280",
      "address": "서울시",
      "photo": "http://sample.bmaster.kro.kr/photos/81.jpg"
    },
    {
      "no": 1587142805747,
      "name": "Zoe Wood",
      "tel": "010-3456-8279",
      "address": "서울시",
      "photo": "http://sample.bmaster.kro.kr/photos/80.jpg"
    },
    {
      "no": 1587142805746,
      "name": "Amoni Turner",
      "tel": "010-3456-8278",
      "address": "서울시",
      "photo": "http://sample.bmaster.kro.kr/photos/79.jpg"
    },
    {
      "no": 1587142805745,
      "name": "Rai Phillips",
      "tel": "010-3456-8277",
      "address": "서울시",
      "photo": "http://sample.bmaster.kro.kr/photos/78.jpg"
    },
    {
      "no": 1587142805744,
      "name": "Ray Reed",
      "tel": "010-3456-8276",
      "address": "서울시",
      "photo": "http://sample.bmaster.kro.kr/photos/77.jpg"
    },
    {
      "no": 1587142805743,
      "name": "Sophia Howard",
      "tel": "010-3456-8275",
      "address": "서울시",
      "photo": "http://sample.bmaster.kro.kr/photos/76.jpg"
    },
    {
      "no": 1587142805742,
      "name": "Remy Perry",
      "tel": "010-3456-8274",
      "address": "서울시",
      "photo": "http://sample.bmaster.kro.kr/photos/75.jpg"
    },
    {
      "no": 1587142805741,
      "name": "Penelope Adams",
      "tel": "010-3456-8273",
      "address": "서울시",
      "photo": "http://sample.bmaster.kro.kr/photos/74.jpg"
    },
    {
      "no": 1587142805740,
      "name": "Nivea Bailey",
      "tel": "010-3456-8272",
      "address": "서울시",
      "photo": "http://sample.bmaster.kro.kr/photos/73.jpg"
    },
    {
      "no": 1587142805739,
      "name": "Le Johnson",
      "tel": "010-3456-8271",
      "address": "서울시",
      "photo": "http://sample.bmaster.kro.kr/photos/72.jpg"
    },
    {
      "no": 1587142805738,
      "name": "Lyanne Carter",
      "tel": "010-3456-8270",
      "address": "서울시",
      "photo": "http://sample.bmaster.kro.kr/photos/71.jpg"
    },
    {
      "no": 1587142805737,
      "name": "Kelley Howard",
      "tel": "010-3456-8269",
      "address": "서울시",
      "photo": "http://sample.bmaster.kro.kr/photos/70.jpg"
    },
    {
      "no": 1587142805736,
      "name": "Lai Phillips",
      "tel": "010-3456-8268",
      "address": "서울시",
      "photo": "http://sample.bmaster.kro.kr/photos/69.jpg"
    },
    {
      "no": 1587142805735,
      "name": "Harper Lewis",
      "tel": "010-3456-8267",
      "address": "서울시",
      "photo": "http://sample.bmaster.kro.kr/photos/68.jpg"
    },
    {
      "no": 1587142805734,
      "name": "Jain Cruz",
      "tel": "010-3456-8266",
      "address": "서울시",
      "photo": "http://sample.bmaster.kro.kr/photos/67.jpg"
    },
    {
      "no": 1587142805733,
      "name": "Rose Baker",
      "tel": "010-3456-8265",
      "address": "서울시",
      "photo": "http://sample.bmaster.kro.kr/photos/66.jpg"
    },
    {
      "no": 1587142805732,
      "name": "Zari Collins",
      "tel": "010-3456-8264",
      "address": "서울시",
      "photo": "http://sample.bmaster.kro.kr/photos/65.jpg"
    },
    {
      "no": 1587142805731,
      "name": "Sophie Lewis",
      "tel": "010-3456-8263",
      "address": "서울시",
      "photo": "http://sample.bmaster.kro.kr/photos/64.jpg"
    },
    {
      "no": 1587142805730,
      "name": "Rosebud Taylor",
      "tel": "010-3456-8262",
      "address": "서울시",
      "photo": "http://sample.bmaster.kro.kr/photos/63.jpg"
    },
    {
      "no": 1587142805729,
      "name": "Rhu Reed",
      "tel": "010-3456-8261",
      "address": "서울시",
      "photo": "http://sample.bmaster.kro.kr/photos/62.jpg"
    },
    {
      "no": 1587142805728,
      "name": "Sean Robinson",
      "tel": "010-3456-8260",
      "address": "서울시",
      "photo": "http://sample.bmaster.kro.kr/photos/61.jpg"
    },
    {
      "no": 1587142805727,
      "name": "Gladys Bell",
      "tel": "010-3456-8259",
      "address": "서울시",
      "photo": "http://sample.bmaster.kro.kr/photos/60.jpg"
    },
    {
      "no": 1587142805726,
      "name": "Nade Williams",
      "tel": "010-3456-8258",
      "address": "서울시",
      "photo": "http://sample.bmaster.kro.kr/photos/59.jpg"
    },
    {
      "no": 1587142805725,
      "name": "Mila Hughes",
      "tel": "010-3456-8257",
      "address": "서울시",
      "photo": "http://sample.bmaster.kro.kr/photos/58.jpg"
    },
    {
      "no": 1587142805724,
      "name": "Landon Anderson",
      "tel": "010-3456-8256",
      "address": "서울시",
      "photo": "http://sample.bmaster.kro.kr/photos/57.jpg"
    },
    {
      "no": 1587142805723,
      "name": "Tonya Harris",
      "tel": "010-3456-8255",
      "address": "서울시",
      "photo": "http://sample.bmaster.kro.kr/photos/56.jpg"
    },
    {
      "no": 1587142805722,
      "name": "Courtney Edwards",
      "tel": "010-3456-8254",
      "address": "서울시",
      "photo": "http://sample.bmaster.kro.kr/photos/55.jpg"
    },
    {
      "no": 1587142805721,
      "name": "Feron Brown",
      "tel": "010-3456-8253",
      "address": "서울시",
      "photo": "http://sample.bmaster.kro.kr/photos/54.jpg"
    },
    {
      "no": 1587142805720,
      "name": "Engel Morgan",
      "tel": "010-3456-8252",
      "address": "서울시",
      "photo": "http://sample.bmaster.kro.kr/photos/53.jpg"
    },
    {
      "no": 1587142805719,
      "name": "Arrietty Miller",
      "tel": "010-3456-8251",
      "address": "서울시",
      "photo": "http://sample.bmaster.kro.kr/photos/52.jpg"
    },
    {
      "no": 1587142805718,
      "name": "Addison Powell",
      "tel": "010-3456-8250",
      "address": "서울시",
      "photo": "http://sample.bmaster.kro.kr/photos/51.jpg"
    },
    {
      "no": 1587142805717,
      "name": "Evon Barnes",
      "tel": "010-3456-8249",
      "address": "서울시",
      "photo": "http://sample.bmaster.kro.kr/photos/50.jpg"
    },
    {
      "no": 1587142805716,
      "name": "Sadie Parker",
      "tel": "010-3456-8248",
      "address": "서울시",
      "photo": "http://sample.bmaster.kro.kr/photos/49.jpg"
    },
    {
      "no": 1587142805715,
      "name": "Raye Martinez",
      "tel": "010-3456-8247",
      "address": "서울시",
      "photo": "http://sample.bmaster.kro.kr/photos/48.jpg"
    },
    {
      "no": 1587142805714,
      "name": "Pita Baker",
      "tel": "010-3456-8246",
      "address": "서울시",
      "photo": "http://sample.bmaster.kro.kr/photos/47.jpg"
    },
    {
      "no": 1587142805713,
      "name": "Kenyatta Cooper",
      "tel": "010-3456-8245",
      "address": "서울시",
      "photo": "http://sample.bmaster.kro.kr/photos/46.jpg"
    },
    {
      "no": 1587142805712,
      "name": "Killion Moore",
      "tel": "010-3456-8244",
      "address": "서울시",
      "photo": "http://sample.bmaster.kro.kr/photos/45.jpg"
    },
    {
      "no": 1587142805711,
      "name": "Kace Stewart",
      "tel": "010-3456-8243",
      "address": "서울시",
      "photo": "http://sample.bmaster.kro.kr/photos/44.jpg"
    },
    {
      "no": 1587142805710,
      "name": "Tracy King",
      "tel": "010-3456-8242",
      "address": "서울시",
      "photo": "http://sample.bmaster.kro.kr/photos/43.jpg"
    },
    {
      "no": 1587142805709,
      "name": "Noel Mitchell",
      "tel": "010-3456-8241",
      "address": "서울시",
      "photo": "http://sample.bmaster.kro.kr/photos/42.jpg"
    },
    {
      "no": 1587142805708,
      "name": "Mallie Allen",
      "tel": "010-3456-8240",
      "address": "서울시",
      "photo": "http://sample.bmaster.kro.kr/photos/41.jpg"
    },
    {
      "no": 1587142805707,
      "name": "Keeta Wilson",
      "tel": "010-3456-8239",
      "address": "서울시",
      "photo": "http://sample.bmaster.kro.kr/photos/40.jpg"
    },
    {
      "no": 1587142805706,
      "name": "Kassie Sanders",
      "tel": "010-3456-8238",
      "address": "서울시",
      "photo": "http://sample.bmaster.kro.kr/photos/39.jpg"
    },
    {
      "no": 1587142805705,
      "name": "Korra Gray",
      "tel": "010-3456-8237",
      "address": "서울시",
      "photo": "http://sample.bmaster.kro.kr/photos/38.jpg"
    },
    {
      "no": 1587142805704,
      "name": "Charlotte Brown",
      "tel": "010-3456-8236",
      "address": "서울시",
      "photo": "http://sample.bmaster.kro.kr/photos/37.jpg"
    },
    {
      "no": 1587142805703,
      "name": "Kaelyn Williams",
      "tel": "010-3456-8235",
      "address": "서울시",
      "photo": "http://sample.bmaster.kro.kr/photos/36.jpg"
    },
    {
      "no": 1587142805702,
      "name": "Amaya Young",
      "tel": "010-3456-8234",
      "address": "서울시",
      "photo": "http://sample.bmaster.kro.kr/photos/35.jpg"
    },
    {
      "no": 1587142805701,
      "name": "Bailey Howard",
      "tel": "010-3456-8233",
      "address": "서울시",
      "photo": "http://sample.bmaster.kro.kr/photos/34.jpg"
    },
    {
      "no": 1587142805700,
      "name": "Megan Brooks",
      "tel": "010-3456-8232",
      "address": "서울시",
      "photo": "http://sample.bmaster.kro.kr/photos/33.jpg"
    },
    {
      "no": 1587142805699,
      "name": "Priyal Powell",
      "tel": "010-3456-8231",
      "address": "서울시",
      "photo": "http://sample.bmaster.kro.kr/photos/32.jpg"
    },
    {
      "no": 1587142805698,
      "name": "Lina Scott",
      "tel": "010-3456-8230",
      "address": "서울시",
      "photo": "http://sample.bmaster.kro.kr/photos/31.jpg"
    },
    {
      "no": 1587142805697,
      "name": "Drew Hill",
      "tel": "010-3456-8229",
      "address": "서울시",
      "photo": "http://sample.bmaster.kro.kr/photos/30.jpg"
    },
    {
      "no": 1587142805696,
      "name": "Blake Miller",
      "tel": "010-3456-8228",
      "address": "서울시",
      "photo": "http://sample.bmaster.kro.kr/photos/29.jpg"
    },
    {
      "no": 1587142805695,
      "name": "Serin Baker",
      "tel": "010-3456-8227",
      "address": "서울시",
      "photo": "http://sample.bmaster.kro.kr/photos/28.jpg"
    },
    {
      "no": 1587142805694,
      "name": "Sa Richardson",
      "tel": "010-3456-8226",
      "address": "서울시",
      "photo": "http://sample.bmaster.kro.kr/photos/27.jpg"
    },
    {
      "no": 1587142805693,
      "name": "Maired Watso",
      "tel": "010-3456-8225",
      "address": "서울시",
      "photo": "http://sample.bmaster.kro.kr/photos/26.jpg"
    },
    {
      "no": 1587142805692,
      "name": "Rachel Ramirez",
      "tel": "010-3456-8224",
      "address": "서울시",
      "photo": "http://sample.bmaster.kro.kr/photos/25.jpg"
    },
    {
      "no": 1587142805691,
      "name": "Khalea Butler",
      "tel": "010-3456-8223",
      "address": "서울시",
      "photo": "http://sample.bmaster.kro.kr/photos/24.jpg"
    },
    {
      "no": 1587142805690,
      "name": "Nahid Smith",
      "tel": "010-3456-8222",
      "address": "서울시",
      "photo": "http://sample.bmaster.kro.kr/photos/23.jpg"
    },
    {
      "no": 1587142805689,
      "name": "Maima Murphy",
      "tel": "010-3456-8221",
      "address": "서울시",
      "photo": "http://sample.bmaster.kro.kr/photos/22.jpg"
    },
    {
      "no": 1587142805688,
      "name": "Fanny Ramirez",
      "tel": "010-3456-8220",
      "address": "서울시",
      "photo": "http://sample.bmaster.kro.kr/photos/21.jpg"
    },
    {
      "no": 1587142805687,
      "name": "Koryne Phillips",
      "tel": "010-3456-8219",
      "address": "서울시",
      "photo": "http://sample.bmaster.kro.kr/photos/20.jpg"
    },
    {
      "no": 1587142805686,
      "name": "Lauren Gray",
      "tel": "010-3456-8218",
      "address": "서울시",
      "photo": "http://sample.bmaster.kro.kr/photos/19.jpg"
    },
    {
      "no": 1587142805685,
      "name": "Kim Cook",
      "tel": "010-3456-8217",
      "address": "서울시",
      "photo": "http://sample.bmaster.kro.kr/photos/18.jpg"
    },
    {
      "no": 1587142805684,
      "name": "Jermyn Martinez",
      "tel": "010-3456-8216",
      "address": "서울시",
      "photo": "http://sample.bmaster.kro.kr/photos/17.jpg"
    },
    {
      "no": 1587142805683,
      "name": "Maya Campbell",
      "tel": "010-3456-8215",
      "address": "서울시",
      "photo": "http://sample.bmaster.kro.kr/photos/16.jpg"
    },
    {
      "no": 1587142805682,
      "name": "Leigh Robinson",
      "tel": "010-3456-8214",
      "address": "서울시",
      "photo": "http://sample.bmaster.kro.kr/photos/15.jpg"
    },
    {
      "no": 1587142805681,
      "name": "Sun Robinson",
      "tel": "010-3456-8213",
      "address": "서울시",
      "photo": "http://sample.bmaster.kro.kr/photos/14.jpg"
    },
    {
      "no": 1587142805680,
      "name": "Aki Brooks",
      "tel": "010-3456-8212",
      "address": "서울시",
      "photo": "http://sample.bmaster.kro.kr/photos/13.jpg"
    },
    {
      "no": 1587142805679,
      "name": "Stella Campbell",
      "tel": "010-3456-8211",
      "address": "서울시",
      "photo": "http://sample.bmaster.kro.kr/photos/12.jpg"
    },
    {
      "no": 1587142805678,
      "name": "Hailey James",
      "tel": "010-3456-8210",
      "address": "서울시",
      "photo": "http://sample.bmaster.kro.kr/photos/11.jpg"
    },
    {
      "no": 1587142805677,
      "name": "Shelley Phillips",
      "tel": "010-3456-8209",
      "address": "서울시",
      "photo": "http://sample.bmaster.kro.kr/photos/10.jpg"
    },
    {
      "no": 1587142805676,
      "name": "London Morgan",
      "tel": "010-3456-8208",
      "address": "서울시",
      "photo": "http://sample.bmaster.kro.kr/photos/9.jpg"
    },
    {
      "no": 1587142805675,
      "name": "Carrie Martinez",
      "tel": "010-3456-8207",
      "address": "서울시",
      "photo": "http://sample.bmaster.kro.kr/photos/8.jpg"
    },
    {
      "no": 1587142805674,
      "name": "Rana Gray",
      "tel": "010-3456-8206",
      "address": "서울시",
      "photo": "http://sample.bmaster.kro.kr/photos/7.jpg"
    },
    {
      "no": 1587142805673,
      "name": "Ariana Butler",
      "tel": "010-3456-8205",
      "address": "서울시",
      "photo": "http://sample.bmaster.kro.kr/photos/6.jpg"
    },
    {
      "no": 1587142805672,
      "name": "Quan Lee",
      "tel": "010-3456-8204",
      "address": "서울시",
      "photo": "http://sample.bmaster.kro.kr/photos/5.jpg"
    },
    {
      "no": 1587142805671,
      "name": "Akiyama Nelson",
      "tel": "010-3456-8203",
      "address": "서울시",
      "photo": "http://sample.bmaster.kro.kr/photos/4.jpg"
    },
    {
      "no": 1587142805670,
      "name": "Amari Hall",
      "tel": "010-3456-8202",
      "address": "서울시",
      "photo": "http://sample.bmaster.kro.kr/photos/3.jpg"
    },
    {
      "no": 1587142805669,
      "name": "Morgan Martin",
      "tel": "010-3456-8201",
      "address": "서울시",
      "photo": "http://sample.bmaster.kro.kr/photos/2.jpg"
    },
    {
      "no": 1587142805668,
      "name": "Kel Fisher",
      "tel": "010-3456-8200",
      "address": "서울시",
      "photo": "http://sample.bmaster.kro.kr/photos/1.jpg"
    }
  ]
}
